beyondllm/__init__.py
beyondllm/embeddings/__init__.py
beyondllm/embeddings/azure.py
beyondllm/embeddings/base.py
beyondllm/embeddings/finetune.py
beyondllm/embeddings/gemini_embed.py
beyondllm/embeddings/hf.py
beyondllm/embeddings/hf_inference.py
beyondllm/embeddings/openaiembed.py
beyondllm/embeddings/qdrantfast.py
beyondllm/embeddings/utils.py
beyondllm/generator/__init__.py
beyondllm/generator/base.py
beyondllm/generator/generate.py
beyondllm/index/base.py
beyondllm/llms/__init__.py
beyondllm/llms/azurechat.py
beyondllm/llms/base.py
beyondllm/llms/chatgroq.py
beyondllm/llms/chatopenai.py
beyondllm/llms/claude.py
beyondllm/llms/gemini.py
beyondllm/llms/gpt4o.py
beyondllm/llms/hf.py
beyondllm/llms/multimodal.py
beyondllm/llms/ollama.py
beyondllm/loaders/base.py
beyondllm/loaders/llamaParseLoader.py
beyondllm/loaders/notionLoader.py
beyondllm/loaders/simpleLoader.py
beyondllm/loaders/urlLoader.py
beyondllm/loaders/youtubeLoader.py
beyondllm/memory/__init__.py
beyondllm/memory/base.py
beyondllm/memory/chatBufferMemory.py
beyondllm/observe/__init__.py
beyondllm/observe/observe.py
beyondllm/retrieve.py
beyondllm/retrievers/base.py
beyondllm/retrievers/crossEncoderReranker.py
beyondllm/retrievers/flagReranker.py
beyondllm/retrievers/hybridRetriever.py
beyondllm/retrievers/normalRetriever.py
beyondllm/retrievers/utils.py
beyondllm/source.py
beyondllm/utils.py
beyondllm/vectordb/__init__.py
beyondllm/vectordb/base.py
beyondllm/vectordb/chroma.py
beyondllm/vectordb/pinecone.py
beyondllm/vectordb/weaviate.py
beyondllm-0.2.3.dist-info/LICENSE
beyondllm-0.2.3.dist-info/METADATA
beyondllm-0.2.3.dist-info/WHEEL
beyondllm-0.2.3.dist-info/RECORD
