Metadata-Version: 2.1
Name: beyondllm
Version: 0.2.3
Summary: Beyond LLM is an toolkit to Build Experiment Evaluate and Observe RAG pipelines
Author: AI Planet
Author-email: tech@aiplanet.com
Requires-Python: >=3.8.1,<4.0
Classifier: Programming Language :: Python :: 3
Classifier: Programming Language :: Python :: 3.9
Classifier: Programming Language :: Python :: 3.10
Classifier: Programming Language :: Python :: 3.11
Classifier: Programming Language :: Python :: 3.12
Requires-Dist: llama-index (==0.10.27)
Requires-Dist: llama-index-embeddings-gemini (==0.1.6)
Requires-Dist: nltk (==3.8.1)
Requires-Dist: numpy (==1.26.4)
Requires-Dist: openai (==1.20.0)
Requires-Dist: pandas (==2.0.3)
Requires-Dist: pydantic (>=1.10.5,<2)
Requires-Dist: pypdf (==4.2.0)
Requires-Dist: pysbd (==0.3.4)
Requires-Dist: pyyaml (==6.0.1)
Requires-Dist: regex (==2024.4.16)
Requires-Dist: sqlalchemy (==2.0.29)
Requires-Dist: tiktoken (==0.6.0)
